civstation/__init__.py
civstation/offset.py
civstation/point.py
civstation/stations.py
civstation-0.2.2.dist-info/licenses/LICENSE.txt
civstation-0.2.2.dist-info/METADATA
civstation-0.2.2.dist-info/WHEEL
civstation-0.2.2.dist-info/top_level.txt
civstation-0.2.2.dist-info/RECORD
