Metadata-Version: 2.4
Name: civstation
Version: 0.2.2
Summary: Support for stationing used in civil plans
Author-email: Scott Windsor <windsorwindsor2@protonmail.com>
License: MIT License
Project-URL: Homepage, https://github.com/windsorwindsor2/civstation
Classifier: Programming Language :: Python :: 3
Classifier: License :: OSI Approved :: MIT License
Classifier: Operating System :: OS Independent
Classifier: Topic :: Scientific/Engineering
Requires-Python: >=3.7
License-File: LICENSE.txt
Dynamic: license-file
